{
  "_fv": 57,
  "_type": "recipe",
  "definition": {
    "recipeType": "Crafting",
    "recipeRetstackSize": 1,
    "group": "grass_block",
    "cookingBookCategory": "MISC",
    "xpReward": 0.0,
    "cookingTime": 200,
    "craftingBookCategory": "MISC",
    "recipeShapeless": false,
    "recipeSlots": [
      {
        "value": ""
      },
      {
        "value": ""
      },
      {
        "value": ""
      },
      {
        "value": ""
      },
      {
        "value": "Items.WHEAT_SEEDS"
      },
      {
        "value": ""
      },
      {
        "value": ""
      },
      {
        "value": "Blocks.DIRT"
      },
      {
        "value": ""
      }
    ],
    "recipeReturnStack": {
      "value": "Blocks.GRASS"
    },
    "name": "grass_block_recipe",
    "namespace": "minecraft"
  }
}