{
  "_fv": 57,
  "_type": "recipe",
  "definition": {
    "recipeType": "Crafting",
    "recipeRetstackSize": 1,
    "group": "iron_glass_boots",
    "cookingBookCategory": "MISC",
    "xpReward": 0.0,
    "cookingTime": 200,
    "craftingBookCategory": "MISC",
    "recipeShapeless": false,
    "recipeSlots": [
      {
        "value": "Blocks.GLASS"
      },
      {
        "value": "Blocks.GLASS"
      },
      {
        "value": "Blocks.GLASS"
      },
      {
        "value": "Items.IRON_INGOT"
      },
      {
        "value": "CUSTOM:GlassArmor.boots"
      },
      {
        "value": "Items.IRON_INGOT"
      },
      {
        "value": "Items.IRON_INGOT"
      },
      {
        "value": ""
      },
      {
        "value": "Items.IRON_INGOT"
      }
    ],
    "recipeReturnStack": {
      "value": "CUSTOM:IronGlassArmor.boots"
    },
    "name": "iron_glass_boots_recipe",
    "namespace": "mod"
  }
}